paldaque/__init__.py
paldaque/api_experiment.py
paldaque/api_experiment_run.py
paldaque/api_experiment_run_instance.py
paldaque/api_experiment_run_phase.py
paldaque/api_muscle_action.py
paldaque/cli.py
paldaque/util.py
paldaque-3.5.5.dist-info/METADATA
paldaque-3.5.5.dist-info/WHEEL
paldaque-3.5.5.dist-info/entry_points.txt
paldaque-3.5.5.dist-info/top_level.txt
paldaque-3.5.5.dist-info/RECORD
