Metadata-Version: 2.4
Name: paldaque
Version: 3.5.5
Summary: PalDaQue, the command line query tool for palaestrAI databases
Author-email: The ARL Developers <stephan.balduin@offis.de>
Project-URL: Homepage, http://docs.palaestr.ai
Classifier: Development Status :: 4 - Beta
Classifier: Intended Audience :: Science/Research
Classifier: License :: OSI Approved :: GNU Lesser General Public License v2 (LGPLv2)
Classifier: Natural Language :: English
Classifier: Operating System :: POSIX :: Linux
Classifier: Programming Language :: Python
Classifier: Programming Language :: Python :: 3
Classifier: Programming Language :: Python :: 3.8
Classifier: Programming Language :: Python :: 3.9
Classifier: Topic :: Scientific/Engineering
Classifier: Topic :: Scientific/Engineering :: Artificial Intelligence
Requires-Python: >=3.10
Requires-Dist: click
Requires-Dist: palaestrai
Requires-Dist: sqlalchemy
Requires-Dist: pandas
Provides-Extra: dev
Requires-Dist: black==22.3.0; extra == "dev"
Requires-Dist: build; extra == "dev"
Requires-Dist: coverage; extra == "dev"
Requires-Dist: setuptools; extra == "dev"
Requires-Dist: sphinx; extra == "dev"
Requires-Dist: twine; extra == "dev"
